icinga_passive/__init__.py
icinga_passive/icinga_passive.py
icinga_passive/lib_presets.py
icinga_passive-1.0.0.dev1.data/scripts/icinga_passive.py
icinga_passive-1.0.0.dev1.data/scripts/lib_presets.py
icinga_passive-1.0.0.dev1.dist-info/LICENSE
icinga_passive-1.0.0.dev1.dist-info/METADATA
icinga_passive-1.0.0.dev1.dist-info/WHEEL
icinga_passive-1.0.0.dev1.dist-info/top_level.txt
icinga_passive-1.0.0.dev1.dist-info/RECORD
