Metadata-Version: 2.1
Name: icinga-passive
Version: 1.0.0.dev1
Summary: Tool to send monitoring metrics pasively to Icinga2
Home-page: https://github.com/julenl/icinga_passive
Author: Julen Larrucea
Author-email: code@larrucea.eu
License: GNU General Public License v2 (GPLv2)
Download-URL: https://github.com/julenl/icinga_passive/archive/0.1.tar.gz
Keywords: icinga,icinga2,passive,monitoring,passive
Platform: UNKNOWN
Classifier: Operating System :: POSIX
Classifier: Programming Language :: Python
Classifier: Programming Language :: Python :: 2
Classifier: Programming Language :: Python :: 3
Classifier: Topic :: System :: Systems Administration
